django_img_mobile_vv/__init__.py
django_img_mobile_vv/apps.py
django_img_mobile_vv/context_processors.py
django_img_mobile_vv/middleware.py
django_img_mobile_vv/utils.py
django_img_mobile_vv/templatetags/__init__.py
django_img_mobile_vv/templatetags/static_mobile.py
django_img_mobile_vv-0.1.0.dist-info/LICENSE.txt
django_img_mobile_vv-0.1.0.dist-info/METADATA
django_img_mobile_vv-0.1.0.dist-info/WHEEL
django_img_mobile_vv-0.1.0.dist-info/top_level.txt
django_img_mobile_vv-0.1.0.dist-info/RECORD
